{
  "data": [
    {
      "id": 21685,
      "start_time": "2024-03-07 13:00:00",
      "end_time": "2024-03-07 14:00:00",
      "video_call_token": null,
      "status": "pending",
      "price": 0,
      "trainer": {
        "id": 56,
        "name": "Tamara Emad \u062a\u0645\u0627\u0631\u0627 \u0639\u0645\u0627\u062f",
        "image": "storage\/app\/public\/trainersImages\/Kvz1SO40ZSDsDWVNCTD5hqnwo9yWUKzw9flIUNqO.png"
      }
    },
    {
      "id": 8539,
      "start_time": "2024-02-04 07:00:00",
      "end_time": "2024-02-04 08:00:00",
      "video_call_token": "006d3e3ad9bf2a846beb551b003979a2142IACucqE4BVTd1+IU3csaOtIMvqmLFjId46RFZ8NqMrtqGop+KioAAAAAEACMjwAAcYfAZQEAAQCFR79l",
      "status": "started",
      "price": 0,
      "trainer": {
        "id": 56,
        "name": "Tamara Emad \u062a\u0645\u0627\u0631\u0627 \u0639\u0645\u0627\u062f",
        "image": "storage\/app\/public\/trainersImages\/Kvz1SO40ZSDsDWVNCTD5hqnwo9yWUKzw9flIUNqO.png"
      }
    },
    {
      "id": 8188,
      "start_time": "2024-02-03 12:00:00",
      "end_time": "2024-02-03 13:00:00",
      "video_call_token": "006d3e3ad9bf2a846beb551b003979a2142IABWLXTIJmoFpUEPrXh7OK94+s2Fhee1jMu+TEDqMaNcoYp+KioAAAAAEAD2GwAAQ3y\/ZQEAAQBXPL5l",
      "status": "started",
      "price": 0,
      "trainer": {
        "id": 56,
        "name": "Tamara Emad \u062a\u0645\u0627\u0631\u0627 \u0639\u0645\u0627\u062f",
        "image": "storage\/app\/public\/trainersImages\/Kvz1SO40ZSDsDWVNCTD5hqnwo9yWUKzw9flIUNqO.png"
      }
    },
    {
      "id": 8187,
      "start_time": "2024-02-03 11:00:00",
      "end_time": "2024-02-03 12:00:00",
      "video_call_token": "006d3e3ad9bf2a846beb551b003979a2142IABNTgObOfeYt\/tE30By\/vZaHtfMJgmdP6mJHfOw0wuFNYp+KioAAAAAEACiTAAAM26\/ZQEAAQBHLr5l",
      "status": "started",
      "price": 0,
      "trainer": {
        "id": 56,
        "name": "Tamara Emad \u062a\u0645\u0627\u0631\u0627 \u0639\u0645\u0627\u062f",
        "image": "storage\/app\/public\/trainersImages\/Kvz1SO40ZSDsDWVNCTD5hqnwo9yWUKzw9flIUNqO.png"
      }
    },
    {
      "id": 8055,
      "start_time": "2024-02-03 10:00:00",
      "end_time": "2024-02-03 11:00:00",
      "video_call_token": null,
      "status": "finished",
      "price": 0,
      "trainer": {
        "id": 56,
        "name": "Tamara Emad \u062a\u0645\u0627\u0631\u0627 \u0639\u0645\u0627\u062f",
        "image": "storage\/app\/public\/trainersImages\/Kvz1SO40ZSDsDWVNCTD5hqnwo9yWUKzw9flIUNqO.png"
      }
    },
    {
      "id": 7027,
      "start_time": "2024-01-30 11:30:00",
      "end_time": "2024-01-30 12:30:00",
      "video_call_token": "006d3e3ad9bf2a846beb551b003979a2142IAB3wJS69SGZIOUiE1rLomYLGIOPFD+4GZbQ8aNxyC2IjYp+KioAAAAAEABq3QAAOy+6ZQEAAQBP77hl",
      "status": "started",
      "price": 0,
      "trainer": {
        "id": 56,
        "name": "Tamara Emad \u062a\u0645\u0627\u0631\u0627 \u0639\u0645\u0627\u062f",
        "image": "storage\/app\/public\/trainersImages\/Kvz1SO40ZSDsDWVNCTD5hqnwo9yWUKzw9flIUNqO.png"
      }
    },
    {
      "id": 6781,
      "start_time": "2024-01-29 23:35:00",
      "end_time": "2024-01-30 00:35:00",
      "video_call_token": "006d3e3ad9bf2a846beb551b003979a2142IADnfU93VEkuid0rQKOvK1Y2YXQThHKfdHMH3gCpKBu3cop+KioAAAAAEAApJwEApoe5ZQEAAQC6R7hl",
      "status": "started",
      "price": 0,
      "trainer": {
        "id": 56,
        "name": "Tamara Emad \u062a\u0645\u0627\u0631\u0627 \u0639\u0645\u0627\u062f",
        "image": "storage\/app\/public\/trainersImages\/Kvz1SO40ZSDsDWVNCTD5hqnwo9yWUKzw9flIUNqO.png"
      }
    },
    {
      "id": 6777,
      "start_time": "2024-01-29 21:46:00",
      "end_time": "2024-01-29 22:46:00",
      "video_call_token": "006d3e3ad9bf2a846beb551b003979a2142IABVnWydSZgqpKVAowgw9ncVLFBJ\/7SC5Nnyse8kbSM1o4p+KioAAAAAEACehAEAGW65ZQEAAQAtLrhl",
      "status": "started",
      "price": 0,
      "trainer": {
        "id": 56,
        "name": "Tamara Emad \u062a\u0645\u0627\u0631\u0627 \u0639\u0645\u0627\u062f",
        "image": "storage\/app\/public\/trainersImages\/Kvz1SO40ZSDsDWVNCTD5hqnwo9yWUKzw9flIUNqO.png"
      }
    },
    {
      "id": 6571,
      "start_time": "2024-01-29 16:00:00",
      "end_time": "2024-01-29 17:00:00",
      "video_call_token": "006d3e3ad9bf2a846beb551b003979a2142IAD9aPKos3kICCD+Cztbgz9nwpF4SWImNYj+Bo1ZFU5ceIp+KioAAAAAEAC3cQAAAx25ZQEAAQAX3bdl",
      "status": "started",
      "price": 0,
      "trainer": {
        "id": 56,
        "name": "Tamara Emad \u062a\u0645\u0627\u0631\u0627 \u0639\u0645\u0627\u062f",
        "image": "storage\/app\/public\/trainersImages\/Kvz1SO40ZSDsDWVNCTD5hqnwo9yWUKzw9flIUNqO.png"
      }
    },
    {
      "id": 6572,
      "start_time": "2024-01-29 15:00:00",
      "end_time": "2024-01-29 16:00:00",
      "video_call_token": null,
      "status": "finished",
      "price": 0,
      "trainer": {
        "id": 56,
        "name": "Tamara Emad \u062a\u0645\u0627\u0631\u0627 \u0639\u0645\u0627\u062f",
        "image": "storage\/app\/public\/trainersImages\/Kvz1SO40ZSDsDWVNCTD5hqnwo9yWUKzw9flIUNqO.png"
      }
    }
  ]
}