{
  "project_info": {
    "project_number": "644714333877",
    "project_id": "fitness-strom-1",
    "storage_bucket": "fitness-strom-1.appspot.com"
  },
  "client": [
    {
      "client_info": {
        "mobilesdk_app_id": "1:644714333877:android:569d4dcdd048a372b820fc",
        "android_client_info": {
          "package_name": "com.chi.fitnessStorm"
        }
      },
      "oauth_client": [
        {
          "client_id": "644714333877-hs4gvjria97frfqn3giqnu0agv508i3g.apps.googleusercontent.com",
          "client_type": 1,
          "android_info": {
            "package_name": "com.chi.fitnessStorm",
            "certificate_hash": "b9623ebc4bb3f108392bacde3d149e763fbd7152"
          }
        },
        {
          "client_id": "644714333877-1bqnqk8h7omigcg7n930aft0m62i60jo.apps.googleusercontent.com",
          "client_type": 3
        }
      ],
      "api_key": [
        {
          "current_key": "AIzaSyAQNJPPpwccWSWZuBk-8IJsBcIuMMkuxX8"
        }
      ],
      "services": {
        "appinvite_service": {
          "other_platform_oauth_client": [
            {
              "client_id": "644714333877-1bqnqk8h7omigcg7n930aft0m62i60jo.apps.googleusercontent.com",
              "client_type": 3
            },
            {
              "client_id": "644714333877-6jd09h6n6djp1tkuh9sv7jn5on6dde7b.apps.googleusercontent.com",
              "client_type": 2,
              "ios_info": {
                "bundle_id": "com.afaq.afaqAlnourAcademy"
              }
            }
          ]
        }
      }
    }
  ],
  "configuration_version": "1"
}